prophecyperfect/__init__.py
prophecyperfect/main.py
prophecyperfect/prompts.py
prophecyperfect-2025.12.21163318.dist-info/METADATA
prophecyperfect-2025.12.21163318.dist-info/WHEEL
prophecyperfect-2025.12.21163318.dist-info/top_level.txt
prophecyperfect-2025.12.21163318.dist-info/RECORD
