Metadata-Version: 2.4
Name: prophecyperfect
Version: 2025.12.21163318
Summary: The system takes a brief textual description, prompt, or statement from the user and analyzes it to determine if it correctly expresses a prophetic or visionary statement in the perfect tense. Using p
Author-email: prophecyperfect <hi@eugene.plus>
License: MIT
Project-URL: Homepage, https://github.com/chigwell/prophecyperfect
Requires-Python: >=3.9
Requires-Dist: langchain-llm7>=0.0.0
Requires-Dist: llmatch-messages>=0.0.0
Requires-Dist: langchain-core>=0.3.0
